{
    "list": [
        {
            "Type": 2,
            "Bosses": [
                {
                    "Name": "Valigarmanda",
                    "Picture": {
                        "Large": "/Pictures/Valigarmanda.png",
                        "Small": "/Pictures/Valigarmanda_small.png"
                    },
                    "BGM": [
                        "The Skyruin"
                    ],
                    "Patch": "7.0"
                },
                {
                    "Name": "Zoraal Ja",
                    "Picture": {
                        "Large": "/Pictures/Zoraal.png",
                        "Small": "/Pictures/Zoraal_small.png"
                    },
                    "BGM": [
                        "Seeking Purpose"
                    ],
                    "Patch": "7.0"
                },
                {
                    "Name": "Queen Eternal",
                    "Picture": {
                        "Large": "/Pictures/QueenEternal.png",
                        "Small": "/Pictures/QueenEternal_small.png"
                    },
                    "BGM": [
                        "Paved in Solitude",
                        "Paved with Resolve"
                    ],
                    "Patch": "7.0"
                },
                {
                    "Name": "Zelenia",
                    "Picture": {
                        "Large": "/Pictures/Zelenia.png",
                        "Small": "/Pictures/Zelenia_small.png"
                    },
                    "BGM": [
                        "Roses of May (Dawntrail)"
                    ],
                    "Patch": "7.2"
                },
                {
                    "Name": "Necron",
                    "Picture": {
                        "Large": "/Pictures/Necron.png",
                        "Small": "/Pictures/Necron_small.png"
                    },
                    "BGM": [
                        "Final Fantasy IX: The Final Battle (Dawntrail)"
                    ],
                    "Patch": "7.3"
                },
                {
                    "Name": "Arkveld",
                    "Picture": {
                        "Large": "/Pictures/Arkveld.png",
                        "Small": "/Pictures/Arkveld_small.png"
                    },
                    "BGM": [
                        "Radiant Cry of Life"
                    ],
                    "Patch": "7.35"
                },
                {
                    "Name": "Doomtrain",
                    "Picture": {
                        "Large": "/Pictures/Doomtrain.png",
                        "Small": "/Pictures/Doomtrain_small.png"
                    },
                    "BGM": [
                        "Final Fantasy IX: Battle 2 (Dawntrail)"
                    ],
                    "Patch": "7.4"
                }
            ]
        },
        {
            "Type": 4,
            "Bosses" : [
                {
                    "Name": "Black Cat",
                    "Picture": {
                        "Large": "/Pictures/Yaana.png",
                        "Small": "/Pictures/Yaana_small.png"
                    },
                    "BGM": [
                        "It's Showtime!"
                    ],
                    "Patch": "7.01"
                },
                {
                    "Name": "Honey B. Lovely",
                    "Picture": {
                        "Large": "/Pictures/Bee.png",
                        "Small": "/Pictures/Bee_small.png"
                    },
                    "BGM": [
                        "Bee My Honey"
                    ],
                    "Patch": "7.01"
                },
                {
                    "Name": "Brute Bomber",
                    "Picture": {
                        "Large": "/Pictures/Brute.png",
                        "Small": "/Pictures/Brute_small.png"
                    },
                    "BGM": [
                        "Burning Souls"
                    ],
                    "Patch": "7.01"
                },
                {
                    "Name": "Wicked Thunder",
                    "Picture": {
                        "Large": "/Pictures/Eutrope.png",
                        "Small": "/Pictures/Eutrope_small.png"
                    },
                    "BGM": [
                        "Give it All",
                        "A Risky Bet"
                    ],
                    "Patch": "7.01"
                },
                {
                    "Name": "Dancing Green",
                    "Picture": {
                        "Large": "/Pictures/Frog.png",
                        "Small": "/Pictures/Frog_small.png"
                    },
                    "BGM": [
                        "Ride the Rhythm"
                    ],
                    "Patch": "7.2"
                },
                {
                    "Name": "Sugar Riot",
                    "Picture": {
                        "Large": "/Pictures/Sugar Riot.png",
                        "Small": "/Pictures/Sugar Riot_small.png"
                    },
                    "BGM": [
                        "Back to the Drawing Board"
                    ],
                    "Patch": "7.2"
                },
                {
                    "Name": "Brute Abominator",
                    "Picture": {
                        "Large": "/Pictures/Brute2.png",
                        "Small": "/Pictures/Brute2_small.png"
                    },
                    "BGM": [
                        "Not Afraid"
                    ],
                    "Patch": "7.2"
                },
                {
                    "Name": "Howling Blade",
                    "Picture": {
                        "Large": "/Pictures/Wolf.png",
                        "Small": "/Pictures/Wolf_small.png"
                    },
                    "BGM": [
                        "Unleashed",
                        "Peerless"
                    ],
                    "Patch": "7.2"
                },
                {
                    "Name": "Vamp Fatale",
                    "Picture": {
                        "Large": "/Pictures/Vamp Fatale.png",
                        "Small": "/Pictures/Vamp Fatale_small.png"
                    },
                    "BGM": [
                        "Sinister"
                    ],
                    "Patch": "7.4"
                },
                {
                    "Name": "The Xtremes (Red Hot & Deep Blue)",
                    "Picture": {
                        "Large": "/Pictures/BJB.png",
                        "Small": "/Pictures/BJB_small.png"
                    },
                    "BGM": [
                        "The Mirror"
                    ],
                    "Patch": "7.4"
                },
                {
                    "Name": "The Tyrant",
                    "Picture": {
                        "Large": "/Pictures/Gilgamesh.png",
                        "Small": "/Pictures/Gilgamesh_small.png"
                    },
                    "BGM": [
                        "Absolute Tyranny"
                    ],
                    "Patch": "7.4"
                },
                {
                    "Name": "Lindwurm",
                    "Picture": {
                        "Large": "/Pictures/Lindwurm.png",
                        "Small": "/Pictures/Lindwurm_small.png"
                    },
                    "BGM": [
                        "Everything Burns",
                        "The Arcadion"
                    ],
                    "Patch": "7.4"
                }
            ]
        },
        {
            "Type": 8,
            "Bosses" : [
                {
                    "Name": "Prishe of the Distant Chains",
                    "Picture": {
                        "Large": "/Pictures/Prishe.png",
                        "Small": "/Pictures/Prishe_small.png"
                    },
                    "BGM": [
                        "Depths of the Soul"
                    ],
                    "Patch": "7.1"
                },
                {
                    "Name": "Fafnir the Forgotten",
                    "Picture": {
                        "Large": "/Pictures/Fafnir.png",
                        "Small": "/Pictures/Fafnir_small.png"
                    },
                    "BGM": [
                        "Battle in the Dungeon #3 (Fafnir)"
                    ],
                    "Patch": "7.1"
                },
                {
                    "Name": "The Ark Angels (MR, EV, HM, GK, TT)",
                    "Picture": {
                        "Large": "/Pictures/ArkAngels.png",
                        "Small": "/Pictures/ArkAngels_small.png"
                    },
                    "BGM": [
                        "Fighters of the Crystal"
                    ],
                    "Patch": "7.1"
                },
                {
                    "Name": "Shadow Lord",
                    "Picture": {
                        "Large": "/Pictures/Shadow Lord.png",
                        "Small": "/Pictures/Shadow Lord_small.png"
                    },
                    "BGM": [
                        "Awakening (Shadow Lord)"
                    ],
                    "Patch": "7.3"
                },
                {
                    "Name": "Faithbound Kirin",
                    "Picture": {
                        "Large": "/Pictures/Faithbound Kirin.png",
                        "Small": "/Pictures/Faithbound Kirin_small.png"
                    },
                    "BGM": [
                        "Tough Battle"
                    ],
                    "Patch": "7.3"
                },
                {
                    "Name": "Ultima, the Feared and Omega, the One",
                    "Picture": {
                        "Large": "/Pictures/UltimaOmega.png",
                        "Small": "/Pictures/UltimaOmega_small.png"
                    },
                    "BGM": [
                        "Turmoil"
                    ],
                    "Patch": "7.3"
                },
                {
                    "Name": "Kam'lanaut",
                    "Picture": {
                        "Large": "/Pictures/Kam.png",
                        "Small": "/Pictures/Kam_small.png"
                    },
                    "BGM": [
                        "Tough Battle (2)"
                    ],
                    "Patch": "7.3"
                },
                {
                    "Name": "Eald'narche",
                    "Picture": {
                        "Large": "/Pictures/Eald.png",
                        "Small": "/Pictures/Eald_small.png"
                    },
                    "BGM": [
                        "Eald'narche",
                        "Belief"
                    ],
                    "Patch": "7.3"
                }
            ]
        }
    ]
}